nodoc/__init__.py
nodoc/nodoc/__init__.py
nodoc/nodoc/const.py
nodoc/nodoc/database/__init__.py
nodoc/nodoc/database/database.py
nodoc/nodoc/database/vectordb.py
nodoc/nodoc/debugger/__init__.py
nodoc/nodoc/debugger/decorator.py
nodoc/nodoc/document/__init__.py
nodoc/nodoc/document/_base.py
nodoc/nodoc/document/base.py
nodoc/nodoc/document/flow_processing.py
nodoc/nodoc/document/markdown.py
nodoc/nodoc/document/pdf.py
nodoc/nodoc/examples/nodoc_node.py
nodoc/nodoc/examples/nodoc_vdb.py
nodoc/nodoc/post_processing/__init__.py
nodoc/nodoc/post_processing/_base.py
nodoc/nodoc/structure/__init__.py
nodoc/nodoc/structure/doc_tree.py
nodoc/nodoc/structure/tree.py
nodoc-1.0.31.dist-info/METADATA
nodoc-1.0.31.dist-info/WHEEL
nodoc-1.0.31.dist-info/top_level.txt
nodoc-1.0.31.dist-info/RECORD
