Metadata-Version: 2.1
Name: nodoc
Version: 1.0.31
Summary: Layer-by-layer manipulation of document data with ease and efficiency.
Author-email: HangBack <3402977740@qq.com>
Project-URL: Homepage, https://github.com/hangback/nodoc
Classifier: Programming Language :: Python :: 3.11
Classifier: License :: OSI Approved :: MIT License
Classifier: Operating System :: OS Independent
Requires-Python: <3.12,>=3.11
